tptest/__init__.py
tptest/cli.py
tptest/commands/__init__.py
tptest/commands/check_api.py
tptest/commands/configure.py
tptest/commands/register.py
tptest/commands/start_batch_test.py
tptest/commands/start_test.py
tptest/utils/__init__.py
tptest/utils/config_loader.py
tptest/utils/disconnect.py
tptest/utils/get_websocket.py
tptest/utils/spinner.py
tptest/utils/waiter.py
tptest-0.1.31.dist-info/LICENSE
tptest-0.1.31.dist-info/METADATA
tptest-0.1.31.dist-info/WHEEL
tptest-0.1.31.dist-info/entry_points.txt
tptest-0.1.31.dist-info/top_level.txt
tptest-0.1.31.dist-info/RECORD
