Metadata-Version: 2.1
Name: tptest
Version: 0.1.31
Summary: A CLI tool for running tasks against IVRs using the TotalPath Tool
Home-page: https://github.com/nopaque/tptest
Author: Nopaque Limited
Author-email: info@nopaque.co.uk
Classifier: Programming Language :: Python :: 3
Classifier: License :: OSI Approved :: MIT License
Classifier: Operating System :: OS Independent
Requires-Python: >=3.12
License-File: LICENSE
Requires-Dist: click
Requires-Dist: websockets
Requires-Dist: asyncclick
